flutter_debugger/__init__.py
pipcli/__init__.py
pipcli/pip_creation.py
pipcli/utils.py
pipcli-1.2.data/scripts/flutterdebugger
pipcli-1.2.data/scripts/pipcli
pipcli-1.2.dist-info/LICENSE
pipcli-1.2.dist-info/METADATA
pipcli-1.2.dist-info/WHEEL
pipcli-1.2.dist-info/top_level.txt
pipcli-1.2.dist-info/RECORD
