Metadata-Version: 2.1
Name: pipcli
Version: 1.2
Summary: create pip package
Home-page: https://github.com/SquarePants1991/flutterdebugger
Author: ocean wang
Author-email: tomcat1991@126.com
License: UNKNOWN
Platform: UNKNOWN
Classifier: Programming Language :: Python :: 3
Classifier: License :: OSI Approved :: MIT License
Classifier: Operating System :: OS Independent
Requires-Dist: coloredlogs
Requires-Dist: fire
